goes16ci/__init__.py
goes16ci/data.py
goes16ci/imager.py
goes16ci/lightning.py
goes16ci/models.py
goes16ci/monitor.py
goes16ci-0.1.3.dist-info/METADATA
goes16ci-0.1.3.dist-info/WHEEL
goes16ci-0.1.3.dist-info/top_level.txt
goes16ci-0.1.3.dist-info/RECORD
