Metadata-Version: 2.1
Name: goes16ci
Version: 0.1.3
Summary: Machine learning benchmark for lightning prediction with GOES16
Home-page: https://github.com/NCAR/goes16ci
Author: David John Gagne
Author-email: dgagne@ucar.edu
License: MIT
Platform: UNKNOWN
Requires-Dist: numpy
Requires-Dist: scipy
Requires-Dist: pandas
Requires-Dist: tensorflow (>=1.15.2)
Requires-Dist: xarray
Requires-Dist: dask
Requires-Dist: pyyaml
Requires-Dist: s3fs
